target_jsonl_webhdfs.py
target_jsonl_webhdfs-0.1.4.4.dist-info/entry_points.txt
target_jsonl_webhdfs-0.1.4.4.dist-info/LICENSE
target_jsonl_webhdfs-0.1.4.4.dist-info/WHEEL
target_jsonl_webhdfs-0.1.4.4.dist-info/METADATA
target_jsonl_webhdfs-0.1.4.4.dist-info/RECORD
