Metadata-Version: 2.1
Name: target-jsonl-webhdfs
Version: 0.1.4.4
Summary: Singer.io target for writing JSON Line files via webhdfs
Home-page: https://github.com/barloc/target-jsonl-webhdfs
Keywords: singer,singer.io,target,etl,meltano,webhdfs
Author: Andy Huynh
Author-email: andy.huynh312@gmail.com
Maintainer: Stanislav Lysikov
Maintainer-email: stave.tx@gmail.com
Requires-Python: >=3.7,<4.0
Classifier: Programming Language :: Python :: 3
Classifier: Programming Language :: Python :: 3.7
Classifier: Programming Language :: Python :: 3.8
Classifier: Programming Language :: Python :: 3.9
Classifier: Programming Language :: Python :: 3.10
Classifier: Programming Language :: Python :: 3.11
Classifier: Programming Language :: Python :: 3 :: Only
Requires-Dist: adjust-precision-for-schema (==0.3.3)
Requires-Dist: hdfs (==2.7.0)
Requires-Dist: jsonschema (==2.6.0)
Requires-Dist: singer-python (==5.8.0)
Project-URL: Repository, https://github.com/barloc/target-jsonl-webhdfs
